{
  "@context": {
    "dcat": "http://www.w3.org/ns/dcat#",
    "dct": "http://purl.org/dc/terms/"
  },
  "@id": "https://identity.nvo987.us/dcat.json",
  "@type": "dcat:Catalog",

  "dct:title": "NVO987 Cultural Heritage Catalog",

  "dct:publisher": {
    "@id": "did:web:identity.nvo987.us"
  },

  "dcat:dataset": [
    {
      "@id": "https://musees.nvo987.eu",
      "@type": "dcat:Dataset",

      "dct:title": "Musees",

      "dcat:landingPage": {
        "@id": "https://musees.nvo987.eu"
      }
    },
    {
      "@id": "https://unesco-fr.nvo987.eu",
      "@type": "dcat:Dataset",

      "dct:title": "UNESCO France",

      "dcat:landingPage": {
        "@id": "https://unesco-fr.nvo987.eu"
      }
    }
  ]
} 
